mlir/execution_engine.py
mlir/ir.py
mlir/passmanager.py
mlir/rewrite.py
mlir/_mlir_libs/__init__.py
mlir/_mlir_libs/_mlir.cpython-312-x86_64-linux-gnu.so
mlir/_mlir_libs/_mlirAsyncPasses.cpython-312-x86_64-linux-gnu.so
mlir/_mlir_libs/_mlirDialectsGPU.cpython-312-x86_64-linux-gnu.so
mlir/_mlir_libs/_mlirDialectsLLVM.cpython-312-x86_64-linux-gnu.so
mlir/_mlir_libs/_mlirDialectsLinalg.cpython-312-x86_64-linux-gnu.so
mlir/_mlir_libs/_mlirDialectsNVGPU.cpython-312-x86_64-linux-gnu.so
mlir/_mlir_libs/_mlirDialectsPDL.cpython-312-x86_64-linux-gnu.so
mlir/_mlir_libs/_mlirDialectsQuant.cpython-312-x86_64-linux-gnu.so
mlir/_mlir_libs/_mlirDialectsSparseTensor.cpython-312-x86_64-linux-gnu.so
mlir/_mlir_libs/_mlirDialectsTransform.cpython-312-x86_64-linux-gnu.so
mlir/_mlir_libs/_mlirExecutionEngine.cpython-312-x86_64-linux-gnu.so
mlir/_mlir_libs/_mlirExecutionEngine.pyi
mlir/_mlir_libs/_mlirGPUPasses.cpython-312-x86_64-linux-gnu.so
mlir/_mlir_libs/_mlirLinalgPasses.cpython-312-x86_64-linux-gnu.so
mlir/_mlir_libs/_mlirPythonTest.cpython-312-x86_64-linux-gnu.so
mlir/_mlir_libs/_mlirRegisterEverything.cpython-312-x86_64-linux-gnu.so
mlir/_mlir_libs/_mlirSparseTensorPasses.cpython-312-x86_64-linux-gnu.so
mlir/_mlir_libs/_mlirTransformInterpreter.cpython-312-x86_64-linux-gnu.so
mlir/_mlir_libs/_pto.cpython-312-x86_64-linux-gnu.so
mlir/_mlir_libs/libMLIRPythonCAPI.so
mlir/_mlir_libs/libMLIRPythonCAPI.so.19.1
mlir/_mlir_libs/_mlir/__init__.pyi
mlir/_mlir_libs/_mlir/ir.pyi
mlir/_mlir_libs/_mlir/passmanager.pyi
mlir/_mlir_libs/_mlir/dialects/pdl.pyi
mlir/_mlir_libs/_mlir/dialects/quant.pyi
mlir/_mlir_libs/_mlir/dialects/transform/__init__.pyi
mlir/dialects/_affine_enum_gen.py
mlir/dialects/_affine_ops_gen.py
mlir/dialects/_amdgpu_enum_gen.py
mlir/dialects/_amdgpu_ops_gen.py
mlir/dialects/_arith_enum_gen.py
mlir/dialects/_arith_ops_gen.py
mlir/dialects/_async_ops_gen.py
mlir/dialects/_bufferization_enum_gen.py
ptoas-0.1.1.dist-info/METADATA
ptoas-0.1.1.dist-info/WHEEL
ptoas-0.1.1.dist-info/top_level.txt
ptoas-0.1.1.dist-info/RECORD
