Metadata-Version: 2.4
Name: ptoas
Version: 0.1.1
Summary: PTO Assembler & Optimizer
Requires-Python: >=3.9
Dynamic: requires-python
Dynamic: summary
